{
  "pageHome": {
    "experience": "Dowiadczenie",
    "portfolioProjects": "Projekty do Portfolio"
  },

  "contactForm": {
    "labelName": "Imi",
    "labelEmail": "Email",
    "labelSubject": "Temat",
    "labelMessage": "Wiadomo",
    "placeholderName": "Daj mi zna kim jeste!",
    "placeholderEmail": "Odpowiem Ci tutaj",
    "placeholderSubject": "Zapytanie o projekt? Informacja zwrotna? Daj mi zna!",
    "placeholderMessage": "Jak mog Ci dzisiaj pom贸c?"
  },

  "contactFormFeedback": {
    "success": "Powodzenie!",
    "messageSent": "Twoja wiadomo zostaa wysana.",
    "name": "Imi",
    "email": "Email",
    "subject": "Temat",
    "missingFields": "Brakujce pola!",
    "pleaseCorrect": "Popraw pola formularza kontaktowego i spr贸buj ponownie.",
    "serverError": "Bd serwera!",
    "messageNotSent": "Wiadomo nie zostaa pomylnie wysana; Spr贸buj ponownie p贸藕niej."
  },

  "contactMap": {
    "letUsTalk": "Porozmawiajmy o niekt贸rych projektach",
    "overCup": "przy fili偶ance kawy ",
    "poland": "Polska"
  },

  "experienceDetails": {
    "goAndSee": "Kliknij aby zobaczy repozytorium GitHub",
    "gitHubRepo": "Repozytorium GitHuba",
    "skillsUsed": "Wykorzystane Umiejtnoci:"
  },

  "experienceModal": {
    "projectInfo": "Informacje i Opis Projektu",
    "close": "Zamknij"
  },

  "experienceSlide": {
    "moreInfo": "Wicej Informacji",
    "goAndSee": "Kliknij aby zobaczy repozytorium GitHub",
    "gitHubRepo": "Repozytorium GitHuba"
  },

  "formSubmit": {
    "sending": "Wysyam...",
    "send": "Wylij",
    "reset": "Wyczy",
    "cancel": "Anuluj"
  },

  "header": {
    "home": "Dom",
    "education": "Edukacja",
    "contact": "Kontakt",
    "pdf": "Wersja PDF",
    "hrefPdf": "/my-cv-pl.pdf"
  },

  "myCertificates": {
    "myCertificates": "Moje Certyfikaty"
  },

  "myEducation": {
    "myEducation": "Moja Edukacja"
  }
}
